patlet/__init__.py
patlet/letters.py
patlet/main.py
patlet-0.0.2.dist-info/LICENSE
patlet-0.0.2.dist-info/METADATA
patlet-0.0.2.dist-info/WHEEL
patlet-0.0.2.dist-info/top_level.txt
patlet-0.0.2.dist-info/RECORD
