Metadata-Version: 2.1
Name: patlet
Version: 0.0.2
Summary: Beautiful Pattern Letters
Home-page: https://github.com/anorprogrammer/patlet
Author: Shahobiddin Anorboyev
Author-email: anorprogrammer1127@gmail.com
License: MIT
Platform: UNKNOWN
Classifier: License :: OSI Approved :: MIT License
Classifier: Programming Language :: Python :: 3
Classifier: Programming Language :: Python :: 3.7
License-File: LICENSE
